fque/__init__.py
fque/fque.py
fque-0.0.4.dist-info/LICENSE
fque-0.0.4.dist-info/METADATA
fque-0.0.4.dist-info/WHEEL
fque-0.0.4.dist-info/top_level.txt
fque-0.0.4.dist-info/RECORD
