Metadata-Version: 2.1
Name: fque
Version: 0.0.4
Summary: A fast and simple queue for inter thread communication
Home-page: https://github.com/perrytec/fque.git
Author: perrytec
Author-email: philip.liedtke@perry.sg
Classifier: Programming Language :: Python :: 3
Classifier: License :: OSI Approved :: MIT License
Classifier: Operating System :: OS Independent
Requires-Python: >=3.6
License-File: LICENSE
